judge0/__init__.py
judge0/api.py
judge0/base_types.py
judge0/clients.py
judge0/common.py
judge0/data.py
judge0/errors.py
judge0/filesystem.py
judge0/retry.py
judge0/submission.py
judge0/utils.py
judge0-0.0.7.dist-info/licenses/LICENSE
judge0-0.0.7.dist-info/METADATA
judge0-0.0.7.dist-info/WHEEL
judge0-0.0.7.dist-info/top_level.txt
judge0-0.0.7.dist-info/RECORD
