Metadata-Version: 2.4
Name: judge0
Version: 0.0.7
Summary: The official Python SDK for Judge0.
Author-email: Judge0 <contact@judge0.com>
Project-URL: Homepage, https://github.com/judge0/judge0-python
Project-URL: Repository, https://github.com/judge0/judge0-python.git
Project-URL: Issues, https://github.com/judge0/judge0-python/issues
Classifier: Intended Audience :: Developers
Classifier: License :: OSI Approved :: MIT License
Classifier: Programming Language :: Python :: 3
Classifier: Programming Language :: Python :: 3.10
Classifier: Programming Language :: Python :: 3.11
Classifier: Programming Language :: Python :: 3.12
Classifier: Operating System :: OS Independent
Classifier: Operating System :: POSIX
Classifier: Operating System :: MacOS
Classifier: Operating System :: POSIX :: Linux
Classifier: Operating System :: Microsoft :: Windows
Classifier: Topic :: Software Development :: Libraries :: Python Modules
Classifier: Typing :: Typed
Requires-Python: >=3.10
License-File: LICENSE
Requires-Dist: requests<3.0.0,>=2.28.0
Requires-Dist: pydantic<3.0.0,>=2.0.0
Dynamic: license-file
